{"name":"debe poder llevar a cabo el login","id":"[engine:junit-jupiter]/[class:starter.saucedemotests.WhenLoginSauceDemo]/[method:loginTest()]","scenarioId":"[engine:junit-jupiter]/[class:starter.saucedemotests.WhenLoginSauceDemo]","testCaseName":"starter.saucedemotests.WhenLoginSauceDemo","methodName":"loginTest","testSteps":[{"number":1,"description":"Actor opens the SauceDemo home page","duration":3069,"startTime":"2024-01-18T19:58:15.169913861-05:00[America/Lima]","result":"SUCCESS","precondition":false,"level":0,"children":[{"number":2,"description":"Actor opens the Sauce demo home page","duration":3021,"startTime":"2024-01-18T19:58:15.210124013-05:00[America/Lima]","result":"SUCCESS","precondition":false,"level":1}]},{"number":3,"description":"Actor write the username: standard_user","duration":405,"startTime":"2024-01-18T19:58:18.247930281-05:00[America/Lima]","result":"SUCCESS","precondition":false,"level":0,"children":[{"number":4,"description":"Actor enters \u0027standard_user\u0027 into username field","duration":385,"startTime":"2024-01-18T19:58:18.264176338-05:00[America/Lima]","result":"SUCCESS","precondition":false,"level":1}]},{"number":5,"description":"Actor write the password: secret_sauce","duration":431,"startTime":"2024-01-18T19:58:18.656418577-05:00[America/Lima]","result":"SUCCESS","precondition":false,"level":0,"children":[{"number":6,"description":"Actor enters \u0027secret_sauce\u0027 then hits [ENTER] into password field","duration":420,"startTime":"2024-01-18T19:58:18.660741250-05:00[America/Lima]","result":"SUCCESS","precondition":false,"level":1}]},{"number":7,"description":"Actor should see title with text value that is equal to: \u003c\"Swag Labs\"\u003e","duration":93,"startTime":"2024-01-18T19:58:19.112859232-05:00[America/Lima]","result":"SUCCESS","precondition":false,"level":0}],"userStory":{"id":"starter.saucedemotests.WhenLoginSauceDemo","storyName":"WhenLoginSauceDemo","displayName":"WhenLoginSauceDemo","storyClassName":"starter.saucedemotests.WhenLoginSauceDemo","path":"WhenLoginSauceDemo","pathElements":[{"name":"WhenLoginSauceDemo","description":"WhenLoginSauceDemo"}],"narrative":"","type":"feature"},"title":"debe poder llevar a cabo el login","tags":[{"name":"Linux","type":"context","displayName":"Linux"},{"name":"Chrome","type":"context","displayName":"Chrome"},{"name":"Chrome, Linux","type":"context","displayName":"Chrome, Linux"}],"startTime":"2024-01-18T19:58:14.714584238-05:00[America/Lima]","duration":3476,"projectKey":"","sessionId":"2ff4b92b96148a56e01048c5cc38bf5f","driver":"chrome:","isManualTestingUpToDate":false,"context":"chrome,linux","manual":false,"testSource":"JUnit5","actors":[{"name":"Actor","can":["browse the web"]}],"order":0,"result":"SUCCESS"}